limc_utils/__init__.py
limc_utils/bark.py
limc_utils/bio.py
limc_utils/jsonl.py
limc_utils/parallel.py
limc_utils-0.0.2.dist-info/LICENSE
limc_utils-0.0.2.dist-info/METADATA
limc_utils-0.0.2.dist-info/WHEEL
limc_utils-0.0.2.dist-info/top_level.txt
limc_utils-0.0.2.dist-info/RECORD
