Metadata-Version: 2.1
Name: limc_utils
Version: 0.0.2
Summary: Personal utilities
Author: Mingchen Li
Author-email: limc.19980301@gmail.com
License: MIT
Classifier: Programming Language :: Python :: 3
Classifier: Programming Language :: Python :: 3.8
Classifier: Programming Language :: Python :: 3.9
Classifier: Programming Language :: Python :: 3.10
Classifier: Programming Language :: Python :: 3.11
Classifier: Programming Language :: Python :: 3.12
Classifier: License :: OSI Approved :: MIT License
Classifier: Operating System :: OS Independent
Requires-Python: >=3.9
License-File: LICENSE
Requires-Dist: pathos ==0.3.2
Requires-Dist: biopython ==1.84
Requires-Dist: pandas <=2.2.2
Provides-Extra: dev
Requires-Dist: pytest ; extra == 'dev'
